<?xml version="1.0" encoding="UTF-8"?>
<gresources>
  <gresource prefix="/org/gnome/builder">
    <file>css/builder.Adwaita.css</file>
    <file>css/markdown.css</file>

    <file>editor/uncrustify/uncrustify.c.cfg</file>

    <file>gtk/menus.ui</file>

    <file alias="icons/16x16/actions/builder-split-tab-symbolic.symbolic.png">../../data/icons/hicolor/16x16/actions/builder-split-tab-symbolic.symbolic.png</file>
    <file alias="icons/32x32/actions/builder-split-tab-symbolic.symbolic.png">../../data/icons/hicolor/32x32/actions/builder-split-tab-symbolic.symbolic.png</file>
    
    <file>js/marked.js</file>
    <file>js/markdown-view.js</file>

    <file alias="keybindings/default.css">../../data/keybindings/default.css</file>
    <file alias="keybindings/emacs.css">../../data/keybindings/emacs.css</file>
    <file alias="keybindings/vim.css">../../data/keybindings/vim.css</file>

    <file alias="ui/gb-command-bar.ui">../../data/ui/gb-command-bar.ui</file>
    <file alias="ui/gb-editor-frame.ui">../../data/ui/gb-editor-frame.ui</file>
    <file alias="ui/gb-editor-settings-widget.ui">../../data/ui/gb-editor-settings-widget.ui</file>
    <file alias="ui/gb-editor-tweak-widget.ui">../../data/ui/gb-editor-tweak-widget.ui</file>
    <file alias="ui/gb-editor-view.ui">../../data/ui/gb-editor-view.ui</file>
    <file alias="ui/gb-editor-workspace.ui">../../data/ui/gb-editor-workspace.ui</file>
    <file alias="ui/gb-view-stack.ui">../../data/ui/gb-view-stack.ui</file>
    <file alias="ui/gb-workbench.ui">../../data/ui/gb-workbench.ui</file>

    <file>ui/gb-command-bar-item.ui</file>
    <file>ui/gb-devhelp-view.ui</file>
    <file>ui/gb-html-view.ui</file>
    <file>ui/gb-preferences-window.ui</file>
    <file>ui/gb-preferences-page-editor.ui</file>
    <file>ui/gb-preferences-page-emacs.ui</file>
    <file>ui/gb-preferences-page-git.ui</file>
    <file>ui/gb-preferences-page-language.ui</file>
    <file>ui/gb-preferences-page-vim.ui</file>
    <file>ui/gb-search-box.ui</file>
    <file>ui/gb-search-display-group.ui</file>
    <file>ui/gb-search-display-row.ui</file>
  </gresource>
</gresources>
